cmem_plugin_mattermost/__init__.py
cmem_plugin_mattermost/workflow/__init__.py
cmem_plugin_mattermost/workflow/mattermost.svg
cmem_plugin_mattermost/workflow/mattermost_plugin.py
cmem_plugin_mattermost-2.3.0.dist-info/METADATA
cmem_plugin_mattermost-2.3.0.dist-info/WHEEL
cmem_plugin_mattermost-2.3.0.dist-info/licenses/LICENSE
cmem_plugin_mattermost-2.3.0.dist-info/RECORD
