Metadata-Version: 2.4
Name: cmem-plugin-mattermost
Version: 2.3.0
Summary: Send messages to Mattermost channels and users.
License: Apache-2.0
License-File: LICENSE
Keywords: eccenca Corporate Memory,plugin,mattermost
Author: eccenca GmbH
Author-email: cmempy-developer@eccenca.com
Requires-Python: >=3.13,<4.0
Classifier: Development Status :: 5 - Production/Stable
Classifier: Environment :: Plugins
Classifier: Intended Audience :: Information Technology
Classifier: License :: OSI Approved :: Apache Software License
Classifier: Programming Language :: Python :: 3
Classifier: Programming Language :: Python :: 3.13
Classifier: Programming Language :: Python :: 3.14
Classifier: Topic :: Software Development :: Libraries :: Python Modules
Requires-Dist: cmem-plugin-base (>=4.15.0,<5.0.0)
Requires-Dist: requests (>=2.32.5,<3.0.0)
Project-URL: Homepage, https://github.com/eccenca/cmem-plugin-mattermost
